xdoctest/__init__.py
xdoctest/__main__.py
xdoctest/__main__.pyi
xdoctest/_tokenize.py
xdoctest/checker.py
xdoctest/checker.pyi
xdoctest/constants.py
xdoctest/constants.pyi
xdoctest/core.py
xdoctest/core.pyi
xdoctest/demo.py
xdoctest/demo.pyi
xdoctest/directive.py
xdoctest/directive.pyi
xdoctest/doctest_example.py
xdoctest/doctest_example.pyi
xdoctest/doctest_part.py
xdoctest/doctest_part.pyi
xdoctest/dynamic_analysis.py
xdoctest/dynamic_analysis.pyi
xdoctest/exceptions.py
xdoctest/exceptions.pyi
xdoctest/global_state.py
xdoctest/global_state.pyi
xdoctest/parser.py
xdoctest/parser.pyi
xdoctest/plugin.py
xdoctest/plugin.pyi
xdoctest/py.typed
xdoctest/runner.py
xdoctest/runner.pyi
xdoctest/static_analysis.py
xdoctest/static_analysis.pyi
xdoctest/docstr/__init__.py
xdoctest/docstr/docscrape_google.py
xdoctest/docstr/docscrape_google.pyi
xdoctest/docstr/docscrape_numpy.py
xdoctest/docstr/docscrape_numpy.pyi
xdoctest/utils/__init__.py
xdoctest/utils/util_asyncio.py
xdoctest/utils/util_asyncio.pyi
xdoctest/utils/util_deprecation.py
xdoctest/utils/util_deprecation.pyi
xdoctest/utils/util_import.py
xdoctest/utils/util_import.pyi
xdoctest/utils/util_misc.py
xdoctest/utils/util_misc.pyi
xdoctest/utils/util_mixins.py
xdoctest/utils/util_mixins.pyi
xdoctest/utils/util_notebook.py
xdoctest/utils/util_notebook.pyi
xdoctest/utils/util_path.py
xdoctest/utils/util_path.pyi
xdoctest/utils/util_str.py
xdoctest/utils/util_str.pyi
xdoctest/utils/util_stream.py
xdoctest/utils/util_stream.pyi
xdoctest-1.3.0.dist-info/licenses/LICENSE
xdoctest-1.3.0.dist-info/METADATA
xdoctest-1.3.0.dist-info/WHEEL
xdoctest-1.3.0.dist-info/entry_points.txt
xdoctest-1.3.0.dist-info/top_level.txt
xdoctest-1.3.0.dist-info/RECORD
